histgram/__init__.py
histgram/attributions.py
histgram/io.py
histgram/losses.py
histgram/marginalize.py
histgram/negatives.py
histgram/performance.py
histgram/test.py
histgram/utils.py
histgram/data/__init__.py
histgram/data/data.py
histgram/data/datasets.py
histgram/data/genome.py
histgram/model/__init__.py
histgram/model/bpnet.py
histgram/model/chrombpnet.py
histgram/model/enformer.py
histgram-0.0.1.dist-info/METADATA
histgram-0.0.1.dist-info/WHEEL
histgram-0.0.1.dist-info/licenses/LICENSE
histgram-0.0.1.dist-info/RECORD
